setup.cfg
setup.py
db_interface/__init__.py
db_interface/company.py
db_interface/engines.py
db_interface/session_handler.py
db_interface.egg-info/PKG-INFO
db_interface.egg-info/SOURCES.txt
db_interface.egg-info/dependency_links.txt
db_interface.egg-info/not-zip-safe
db_interface.egg-info/top_level.txt