Metadata-Version: 2.1
Name: db-interface
Version: 0.0
Summary: CargoCast database interface
Home-page: UNKNOWN
Author-email: pascal.dietrich@cargocast.de
License: UNKNOWN
Platform: UNKNOWN
